README.txt
setup.py
docs/HISTORY.txt
docs/INSTALL.txt
docs/LICENSE.GPL
docs/LICENSE.txt
zopyx/__init__.py
zopyx.tinymceplugins.tinyautosave.egg-info/PKG-INFO
zopyx.tinymceplugins.tinyautosave.egg-info/SOURCES.txt
zopyx.tinymceplugins.tinyautosave.egg-info/dependency_links.txt
zopyx.tinymceplugins.tinyautosave.egg-info/entry_points.txt
zopyx.tinymceplugins.tinyautosave.egg-info/namespace_packages.txt
zopyx.tinymceplugins.tinyautosave.egg-info/not-zip-safe
zopyx.tinymceplugins.tinyautosave.egg-info/requires.txt
zopyx.tinymceplugins.tinyautosave.egg-info/top_level.txt
zopyx/tinymceplugins/__init__.py
zopyx/tinymceplugins/tinyautosave/__init__.py
zopyx/tinymceplugins/tinyautosave/configure.zcml
zopyx/tinymceplugins/tinyautosave/profiles.zcml
zopyx/tinymceplugins/tinyautosave/setuphandlers.py
zopyx/tinymceplugins/tinyautosave/skins.zcml
zopyx/tinymceplugins/tinyautosave/tests.py
zopyx/tinymceplugins/tinyautosave/version.txt
zopyx/tinymceplugins/tinyautosave/browser/__init__.py
zopyx/tinymceplugins/tinyautosave/browser/configure.zcml
zopyx/tinymceplugins/tinyautosave/locales/placeholder
zopyx/tinymceplugins/tinyautosave/profiles/default/metadata.xml
zopyx/tinymceplugins/tinyautosave/profiles/default/skins.xml
zopyx/tinymceplugins/tinyautosave/profiles/default/tinymce.xml
zopyx/tinymceplugins/tinyautosave/profiles/default/zopyx.autosave_various.txt
zopyx/tinymceplugins/tinyautosave/skins/autosave/tinyautosave/editor_plugin.js
zopyx/tinymceplugins/tinyautosave/skins/autosave/tinyautosave/editor_plugin_src.js
zopyx/tinymceplugins/tinyautosave/skins/autosave/tinyautosave/images/progress.gif
zopyx/tinymceplugins/tinyautosave/skins/autosave/tinyautosave/images/progress10.gif
zopyx/tinymceplugins/tinyautosave/skins/autosave/tinyautosave/images/progress11.gif
zopyx/tinymceplugins/tinyautosave/skins/autosave/tinyautosave/images/progress12.gif
zopyx/tinymceplugins/tinyautosave/skins/autosave/tinyautosave/images/progress2.gif
zopyx/tinymceplugins/tinyautosave/skins/autosave/tinyautosave/images/progress3.gif
zopyx/tinymceplugins/tinyautosave/skins/autosave/tinyautosave/images/progress4.gif
zopyx/tinymceplugins/tinyautosave/skins/autosave/tinyautosave/images/progress5.gif
zopyx/tinymceplugins/tinyautosave/skins/autosave/tinyautosave/images/progress6.gif
zopyx/tinymceplugins/tinyautosave/skins/autosave/tinyautosave/images/progress7.gif
zopyx/tinymceplugins/tinyautosave/skins/autosave/tinyautosave/images/progress8.gif
