Metadata-Version: 1.0
Name: zopyx.tinymceplugins.tinyautosave
Version: 1.0
Summary: TinyMCE auto-save plugin for Plone
Home-page: http://pypi.python.org/pypi/zopyx.tinymceplugins.tinyautosave
Author: Andreas Jung
Author-email: info@zopyx.com
License: GPL
Keywords: TinyMCE Plone
Platform: UNKNOWN
Classifier: Framework :: Plone
Classifier: Programming Language :: Python
